[{
  "name": "intens'O",
  "version": "1.0.0",
  "dependencies": {
  },
  "clusters":["analoginput:000C","basic:0000","lorawan:8004","configuration:0050"]
},
{
  "payload_standard_measure": "310A000C00553900000000"
},
  {
    "type": "uplink",
    "description": "uplink standard report containing volt value | payload:310A000C00553941500000",
    "input": {
      "bytes": [
        49, 10,  0, 12, 0,
        85, 57, 65, 80, 0,
        0
      ],
      "fPort": 125,
      "recvTime": "2023-07-19T07:51:25.508306410Z"
    }
  ,
    "output": {
      "data": [
        {
          "variable": "analog//replace",
          "value": 13,
          "date": "2023-07-19T07:51:25.508306410Z"
        }
      ],
      "warnings": [ "" ]
    }
  }
]